wommit/__init__.py
wommit/apihandler.py
wommit/autocomplete.py
wommit/cli.py
wommit/commitman.py
wommit/configman.py
wommit/constants.py
wommit/msgtool.py
wommit/utils/__init__.py
wommit/utils/changelog_gen.py
wommit/utils/decos.py
wommit/utils/exceptions.py
wommit/utils/template_info.json
wommit/utils/utils.py
wommit-20.8.39.dist-info/entry_points.txt
wommit-20.8.39.dist-info/WHEEL
wommit-20.8.39.dist-info/METADATA
wommit-20.8.39.dist-info/RECORD
