Metadata-Version: 2.1
Name: wommit
Version: 20.8.39
Summary: A tool for intuitively writing git commits that adhere to the Conventional Commits standards.
Home-page: https://github.com/bkkp/wommit
License: MIT
Keywords: wommit,git,emoji,github,commit
Author: Zylvian
Author-email: jovlisen@gmail.com
Requires-Python: >=3.8,<4.0
Classifier: License :: OSI Approved :: MIT License
Classifier: Programming Language :: Python :: 3
Classifier: Programming Language :: Python :: 3.8
Requires-Dist: click (>=7.1.2,<8.0.0)
Requires-Dist: emojis (>=0.5.1,<0.6.0)
Requires-Dist: falcon (>=2.0.0,<3.0.0)
Requires-Dist: gitpython (>=3.1.3,<4.0.0)
Requires-Dist: keyring (>=21.2.1,<22.0.0)
Requires-Dist: prompt_toolkit (>=3.0.5,<4.0.0)
Requires-Dist: pycalver (>=202007.36,<202008.0)
Requires-Dist: questionary (>=1.5.2,<2.0.0)
Requires-Dist: requests (>=2.24.0,<3.0.0)
Requires-Dist: webtest (>=2.0.35,<3.0.0)
Project-URL: Repository, https://github.com/bkkp/wommit
